chrome_auth_extractor/__init__.py
chrome_auth_extractor/core.py
chrome_auth_extractor-0.2.0.dist-info/METADATA
chrome_auth_extractor-0.2.0.dist-info/WHEEL
chrome_auth_extractor-0.2.0.dist-info/top_level.txt
chrome_auth_extractor-0.2.0.dist-info/RECORD
