Metadata-Version: 2.4
Name: chrome_auth_extractor
Version: 0.2.0
Summary: Headless Chrome helper: grab cookies and CSRF token from an existing profile
Author-email: hys56 <honestuniversefalling@gmail.com>
Requires-Python: >=3.9
Requires-Dist: requests>=2.28
Requires-Dist: websocket-client>=1.5
Provides-Extra: dev
Requires-Dist: build; extra == "dev"
Requires-Dist: twine; extra == "dev"
Requires-Dist: wheel; extra == "dev"
